economista/__init__.py
economista-0.1.0.dist-info/METADATA
economista-0.1.0.dist-info/WHEEL
economista-0.1.0.dist-info/top_level.txt
economista-0.1.0.dist-info/RECORD
