Metadata-Version: 2.1
Name: economista
Version: 0.1.0
Summary: Descripción breve del proyecto
Author-email: Daniel Limon <dani@dlimon.net>
